keepcli/__init__.py
keepcli/kcliparser.py
keepcli/keep.py
keepcli/version.py
keepcli-1.0.1.data/scripts/keepcli
keepcli-1.0.1.dist-info/METADATA
keepcli-1.0.1.dist-info/RECORD
keepcli-1.0.1.dist-info/WHEEL
keepcli-1.0.1.dist-info/top_level.txt
