Metadata-Version: 2.1
Name: keepcli
Version: 1.0.1
Summary: Simple unofficial Google Keep Interactive Command Line Interpreter
Home-page: https://github.com/mgckind/keepcli
Author: Matias Carrasco Kind
Author-email: mgckind@gmail.com
License: LICENSE.txt
Platform: UNKNOWN
Requires-Dist: gkeepapi (==0.10.9)
Requires-Dist: setuptools (==34.4.0)
Requires-Dist: termcolor (==1.1.0)
Requires-Dist: PyYAML (==3.13)
